{
  "actions": [
    {
      "action": "minecraft:crafting",
      "requirements": {
        "skilling:construction": 27
      },
      "xp": {
        "skilling:construction": 8.2
      }
    },
    {
      "action": "minecraft:break_block",
      "requirements": {
        "skilling:construction": 27
      }
    }
  ],
  "icon": {
    "type": "",
    "displayName": {
      "name": "",
      "translated": false
    },
    "icon": "biomesoplenty:jacaranda_sign",
    "potion": "",
    "scale": 8,
    "skillbookVisible": true
  },
  "item": "biomesoplenty:jacaranda_sign"
}